MANIFEST.in
setup.py
hybrid/__init__.py
hybrid/commands.py
hybrid/exceptions.py
hybrid/metaclass.py
hybrid.egg-info/PKG-INFO
hybrid.egg-info/SOURCES.txt
hybrid.egg-info/dependency_links.txt
hybrid.egg-info/entry_points.txt
hybrid.egg-info/not-zip-safe
hybrid.egg-info/requires.txt
hybrid.egg-info/top_level.txt
hybrid/middlewares/__init__.py
hybrid/skeleton/__init__.py
hybrid/skeleton/test_server.py.tmpl
hybrid/skeleton/project/__init__.py
hybrid/skeleton/project/settings.py
hybrid/skeleton/project/wsgi.py
hybrid/skeleton/project/controllers/__init__.py
hybrid/skeleton/project/controllers/base_handler.py
hybrid/skeleton/project/controllers/example_of_tornado_handlers.py
hybrid/skeleton/project/modules/__init__.py
hybrid/skeleton/project/views/__init__.py
hybrid/tests/__init__.py
hybrid/tests/pb_test.proto
hybrid/tests/test_convert.py
hybrid/util/__init__.py
hybrid/util/db.py
hybrid/util/simple_convert.py
hybrid/util/test_wsgi.py
hybrid/wsgi_app/__init__.py
hybrid/wsgi_app/base_wsgi.py
hybrid/wsgi_app/flask_wsgi.py
hybrid/wsgi_app/tornado_wsgi.py