Metadata-Version: 1.0
Name: hybrid
Version: 1.1.6
Summary: hybrid tools set
Home-page: http://timd.cn/
Author: timchow
Author-email: jordan23nbastar@yeah.net
License: LGPL
Keywords: hybrid server
Platform: UNKNOWN
